README.md
setup.py
gamechain_play/__init__.py
gamechain_play/gp_tictactoe.py
gamechain_play.egg-info/PKG-INFO
gamechain_play.egg-info/SOURCES.txt
gamechain_play.egg-info/dependency_links.txt
gamechain_play.egg-info/requires.txt
gamechain_play.egg-info/top_level.txt