Metadata-Version: 2.1
Name: gamechain-play
Version: 0.0.1.1
Summary: Protocol for playing, recording, and watching games on the BCH blockchain
Home-page: https://github.com/devalbo/gamechain
Author: Albert Boehmler
Author-email: ajboehmler@gmail.com
License: UNKNOWN
Platform: UNKNOWN
Classifier: Programming Language :: Python :: 3
Classifier: License :: OSI Approved :: GNU General Public License v3 (GPLv3)
Classifier: Operating System :: OS Independent
